markdownify_notion/__init__.py
markdownify_notion-0.5.dist-info/LICENSE
markdownify_notion-0.5.dist-info/METADATA
markdownify_notion-0.5.dist-info/WHEEL
markdownify_notion-0.5.dist-info/top_level.txt
markdownify_notion-0.5.dist-info/RECORD
