Metadata-Version: 2.1
Name: markdownify-notion
Version: 0.5
Summary: A small package to markdownify notion blocks.
Home-page: https://github.com/chekos/markdownify-notion
Author: Sergio Sanchez
License: Apache License, Version 2.0
Project-URL: Issues, https://github.com/chekos/markdownify-notion/issues
Project-URL: CI, https://github.com/chekos/markdownify-notion/actions
Project-URL: Changelog, https://github.com/chekos/markdownify-notion/releases
Requires-Python: >=3.6
License-File: LICENSE
Provides-Extra: test
Requires-Dist: pytest ; extra == 'test'
